mkdocs_autorefs-1.1.0.dist-info/METADATA
mkdocs_autorefs-1.1.0.dist-info/WHEEL
mkdocs_autorefs-1.1.0.dist-info/entry_points.txt
mkdocs_autorefs-1.1.0.dist-info/licenses/LICENSE
mkdocs_autorefs/__init__.py
mkdocs_autorefs/debug.py
mkdocs_autorefs/plugin.py
mkdocs_autorefs/py.typed
mkdocs_autorefs/references.py
mkdocs_autorefs-1.1.0.dist-info/RECORD
