Metadata-Version: 2.1
Name: mkdocs-autorefs
Version: 1.1.0
Summary: Automatically link across pages in MkDocs.
Keywords: mkdocs,mkdocs-plugin,docstrings,autodoc
Author-Email: Oleh Prypin <oleh@pryp.in>, =?utf-8?q?Timoth=C3=A9e_Mazzucotelli?= <dev@pawamoy.fr>
License: ISC
Classifier: Development Status :: 4 - Beta
Classifier: Intended Audience :: Developers
Classifier: License :: OSI Approved :: ISC License (ISCL)
Classifier: Programming Language :: Python
Classifier: Programming Language :: Python :: 3
Classifier: Programming Language :: Python :: 3 :: Only
Classifier: Programming Language :: Python :: 3.8
Classifier: Programming Language :: Python :: 3.9
Classifier: Programming Language :: Python :: 3.10
Classifier: Programming Language :: Python :: 3.11
Classifier: Programming Language :: Python :: 3.12
Classifier: Programming Language :: Python :: 3.13
Classifier: Topic :: Documentation
Classifier: Topic :: Software Development
Classifier: Topic :: Software Development :: Documentation
Classifier: Topic :: Utilities
Classifier: Typing :: Typed
Project-URL: Homepage, https://mkdocstrings.github.io/autorefs
Project-URL: Documentation, https://mkdocstrings.github.io/autorefs
Project-URL: Changelog, https://mkdocstrings.github.io/autorefs/changelog
Project-URL: Repository, https://github.com/mkdocstrings/autorefs
Project-URL: Issues, https://github.com/mkdocstrings/autorefs/issues
Project-URL: Discussions, https://github.com/mkdocstrings/autorefs/discussions
Project-URL: Gitter, https://gitter.im/mkdocstrings/autorefs
Requires-Python: >=3.8
Requires-Dist: Markdown>=3.3
Requires-Dist: markupsafe>=2.0.1
Requires-Dist: mkdocs>=1.1
